{
  "cookies": [
    {
      "name": "session-username",
      "value": "standard_user",
      "domain": "www.saucedemo.com",
      "path": "/",
      "expires": 1775457439,
      "httpOnly": false,
      "secure": false,
      "sameSite": "Lax"
    }
  ],
  "origins": [
    {
      "origin": "https://www.saucedemo.com",
      "localStorage": [
        {
          "name": "backtrace-guid",
          "value": "531e4cc2-e73f-4fa6-9050-6269ce139025"
        },
        {
          "name": "backtrace-last-active",
          "value": "1775456839532"
        }
      ]
    }
  ]
}